gittyup/__init__.py
gittyup/cli.py
gittyup/git_operations.py
gittyup/logger.py
gittyup/models.py
gittyup/output.py
gittyup/scanner.py
gittyup-1.2.0.dist-info/METADATA
gittyup-1.2.0.dist-info/WHEEL
gittyup-1.2.0.dist-info/entry_points.txt
gittyup-1.2.0.dist-info/licenses/LICENSE
gittyup-1.2.0.dist-info/RECORD
