Metadata-Version: 2.4
Name: gittyup
Version: 1.2.0
Summary: Automatically discover and update all git repositories in a directory tree
Project-URL: Homepage, https://github.com/mikeckennedy/gittyup
Project-URL: Repository, https://github.com/mikeckennedy/gittyup
Project-URL: Issues, https://github.com/mikeckennedy/gittyup/issues
Author: Michael Kennedy
License: MIT
License-File: LICENSE
Keywords: automation,cli,git,repository,update
Classifier: Development Status :: 4 - Beta
Classifier: Intended Audience :: Developers
Classifier: License :: OSI Approved :: MIT License
Classifier: Programming Language :: Python :: 3
Classifier: Programming Language :: Python :: 3.13
Classifier: Programming Language :: Python :: 3.14
Classifier: Topic :: Software Development :: Version Control :: Git
Classifier: Topic :: Utilities
Requires-Python: >=3.13
Requires-Dist: click>=8.1.0
Requires-Dist: colorama>=0.4.6
Requires-Dist: diskcache>=5.6.3
Requires-Dist: platformdirs>=4.5.0
Provides-Extra: dev
Requires-Dist: pytest-cov>=6.0.0; extra == 'dev'
Requires-Dist: pytest>=8.0.0; extra == 'dev'
Requires-Dist: ruff>=0.8.0; extra == 'dev'
